MANIFEST.in
README.txt
graphmin.py
setup.cfg
setup.py
examples/ex1.n3
examples/rdfs-rules.n3
graphmin.egg-info/PKG-INFO
graphmin.egg-info/SOURCES.txt
graphmin.egg-info/dependency_links.txt
graphmin.egg-info/entry_points.txt
graphmin.egg-info/not-zip-safe
graphmin.egg-info/top_level.txt