Metadata-Version: 1.0
Name: graphmin
Version: 0.1.8
Summary: RDF Graph Minimisation
Home-page: http://river.styx.org/ww/2010/10/graphmin
Author: William Waites
Author-email: ww@styx.org
License: BSD
Platform: UNKNOWN
